README.rst
pypackagery_meta.py
setup.py
packagery/__init__.py
packagery/main.py
packagery/py.typed
pypackagery.egg-info/PKG-INFO
pypackagery.egg-info/SOURCES.txt
pypackagery.egg-info/dependency_links.txt
pypackagery.egg-info/entry_points.txt
pypackagery.egg-info/requires.txt
pypackagery.egg-info/top_level.txt