Metadata-Version: 2.1
Name: pypackagery
Version: 1.0.5
Summary: Package a subset of a monorepo and determine the dependent packages.
Home-page: https://github.com/Parquery/pypackagery
Author: Marko Ristin
Author-email: marko.ristin@gmail.com
License: License :: OSI Approved :: MIT License
Keywords: package monorepo requirements
Platform: UNKNOWN
Classifier: Development Status :: 5 - Production/Stable
Classifier: Intended Audience :: Developers
Classifier: License :: OSI Approved :: MIT License
Classifier: Programming Language :: Python :: 3.5
Classifier: Programming Language :: Python :: 3.6
Classifier: Programming Language :: Python :: 3.7
Classifier: Programming Language :: Python :: 3.8
Provides-Extra: dev
